Workbook
Name Slicer_Category: #N/A
Name Slicer_Region: #N/A
Name Slicer_Salesperson: #N/A

Sheet Datasheet
A1: Order ID | B1: Date | C1: Region | D1: Salesperson | E1: Category | F1: Product | G1: Units | H1: Revenue | I1: Cost | J1: Profit | K1: Profit Margin | L1: Revenue per Units
A2: O001 | B2: 46082 | C2: Kathmandu | D2: Anisha | E2: Electronics | F2: Laptop | G2: 2 | H2: 160000 | I2: 132000 | J2: =SalesData[[#This Row],[Revenue]]-SalesData[[#This Row],[Cost]] -> 28000 | K2: =SalesData[[#This Row],[Profit]]/SalesData[[#This Row],[Revenue]] -> 0.175 | L2: =SalesData[[#This Row],[Revenue]]/SalesData[[#This Row],[Units]] -> 80000
A3: O002 | B3: 46083 | C3: Lalitpur | D3: Rahul | E3: Accessories | F3: Mouse | G3: 12 | H3: 18000 | I3: 10800 | J3: =SalesData[[#This Row],[Revenue]]-SalesData[[#This Row],[Cost]] -> 7200 | K3: =SalesData[[#This Row],[Profit]]/SalesData[[#This Row],[Revenue]] -> 0.4 | L3: =SalesData[[#This Row],[Revenue]]/SalesData[[#This Row],[Units]] -> 1500
A4: O003 | B4: 46085 | C4: Kathmandu | D4: Priya | E4: Electronics | F4: Monitor | G4: 3 | H4: 90000 | I4: 69000 | J4: =SalesData[[#This Row],[Revenue]]-SalesData[[#This Row],[Cost]] -> 21000 | K4: =SalesData[[#This Row],[Profit]]/SalesData[[#This Row],[Revenue]] -> 0.23333333 | L4: =SalesData[[#This Row],[Revenue]]/SalesData[[#This Row],[Units]] -> 30000
A5: O004 | B5: 46087 | C5: Pokhara | D5: Suman | E5: Accessories | F5: Keyboard | G5: 6 | H5: 18000 | I5: 10800 | J5: =SalesData[[#This Row],[Revenue]]-SalesData[[#This Row],[Cost]] -> 7200 | K5: =SalesData[[#This Row],[Profit]]/SalesData[[#This Row],[Revenue]] -> 0.4 | L5: =SalesData[[#This Row],[Revenue]]/SalesData[[#This Row],[Units]] -> 3000
A6: O005 | B6: 46089 | C6: Bharatpur | D6: Riya | E6: Electronics | F6: Webcam | G6: 5 | H6: 30000 | I6: 20000 | J6: =SalesData[[#This Row],[Revenue]]-SalesData[[#This Row],[Cost]] -> 10000 | K6: =SalesData[[#This Row],[Profit]]/SalesData[[#This Row],[Revenue]] -> 0.33333333 | L6: =SalesData[[#This Row],[Revenue]]/SalesData[[#This Row],[Units]] -> 6000
A7: O006 | B7: 46091 | C7: Kathmandu | D7: Anisha | E7: Electronics | F7: Laptop | G7: 1 | H7: 80000 | I7: 66000 | J7: =SalesData[[#This Row],[Revenue]]-SalesData[[#This Row],[Cost]] -> 14000 | K7: =SalesData[[#This Row],[Profit]]/SalesData[[#This Row],[Revenue]] -> 0.175 | L7: =SalesData[[#This Row],[Revenue]]/SalesData[[#This Row],[Units]] -> 80000
A8: O007 | B8: 46093 | C8: Lalitpur | D8: Rahul | E8: Electronics | F8: Monitor | G8: 2 | H8: 60000 | I8: 46000 | J8: =SalesData[[#This Row],[Revenue]]-SalesData[[#This Row],[Cost]] -> 14000 | K8: =SalesData[[#This Row],[Profit]]/SalesData[[#This Row],[Revenue]] -> 0.23333333 | L8: =SalesData[[#This Row],[Revenue]]/SalesData[[#This Row],[Units]] -> 30000
A9: O008 | B9: 46096 | C9: Pokhara | D9: Suman | E9: Electronics | F9: Laptop | G9: 1 | H9: 80000 | I9: 66000 | J9: =SalesData[[#This Row],[Revenue]]-SalesData[[#This Row],[Cost]] -> 14000 | K9: =SalesData[[#This Row],[Profit]]/SalesData[[#This Row],[Revenue]] -> 0.175 | L9: =SalesData[[#This Row],[Revenue]]/SalesData[[#This Row],[Units]] -> 80000
A10: O009 | B10: 46099 | C10: Bharatpur | D10: Riya | E10: Accessories | F10: Mouse | G10: 18 | H10: 27000 | I10: 16200 | J10: =SalesData[[#This Row],[Revenue]]-SalesData[[#This Row],[Cost]] -> 10800 | K10: =SalesData[[#This Row],[Profit]]/SalesData[[#This Row],[Revenue]] -> 0.4 | L10: =SalesData[[#This Row],[Revenue]]/SalesData[[#This Row],[Units]] -> 1500
A11: O010 | B11: 46101 | C11: Kathmandu | D11: Priya | E11: Electronics | F11: Laptop | G11: 2 | H11: 160000 | I11: 132000 | J11: =SalesData[[#This Row],[Revenue]]-SalesData[[#This Row],[Cost]] -> 28000 | K11: =SalesData[[#This Row],[Profit]]/SalesData[[#This Row],[Revenue]] -> 0.175 | L11: =SalesData[[#This Row],[Revenue]]/SalesData[[#This Row],[Units]] -> 80000
A12: O011 | B12: 46103 | C12: Lalitpur | D12: Rahul | E12: Accessories | F12: Keyboard | G12: 10 | H12: 30000 | I12: 18000 | J12: =SalesData[[#This Row],[Revenue]]-SalesData[[#This Row],[Cost]] -> 12000 | K12: =SalesData[[#This Row],[Profit]]/SalesData[[#This Row],[Revenue]] -> 0.4 | L12: =SalesData[[#This Row],[Revenue]]/SalesData[[#This Row],[Units]] -> 3000
A13: O012 | B13: 46105 | C13: Pokhara | D13: Suman | E13: Electronics | F13: Monitor | G13: 4 | H13: 120000 | I13: 92000 | J13: =SalesData[[#This Row],[Revenue]]-SalesData[[#This Row],[Cost]] -> 28000 | K13: =SalesData[[#This Row],[Profit]]/SalesData[[#This Row],[Revenue]] -> 0.23333333 | L13: =SalesData[[#This Row],[Revenue]]/SalesData[[#This Row],[Units]] -> 30000
... A21: O020 | B21: 46124 | C21: Kathmandu | D21: Priya | E21: Electronics | F21: Laptop | G21: 3 | H21: 240000 | I21: 198000 | J21: =SalesData[[#This Row],[Revenue]]-SalesData[[#This Row],[Cost]] -> 42000 | K21: =SalesData[[#This Row],[Profit]]/SalesData[[#This Row],[Revenue]] -> 0.175 | L21: =SalesData[[#This Row],[Revenue]]/SalesData[[#This Row],[Units]] -> 80000

Sheet Analysis
A1: KPI | B1: Value | D1: Salesperson | E1: Revenue | F1: % of Total | G1: Profit | H1: Profit Margin | I1: Business Flag | K1: Region | L1: Revenue | M1: Profit | N1: Profit Margin | P1: Month | Q1: Revenue | R1: Profit | S1: Profit Margin
A2: Total Revenue | B2: =SUM(Datasheet!H:H) -> 1677000 | D2: Anisha | E2: =SUMIFS(Datasheet!$H:$H,Datasheet!$D:$D,Analysis!D2) -> 348000 | F2: =E2/$B$2 -> 0.20751342 | G2: =SUMIFS(Datasheet!$J:$J,Datasheet!$D:$D,Analysis!D2) -> 72000 | H2: =G2/E2 -> 0.20689655 | I2: =IF(H2<25%,"Review","Healthy") -> Review | K2: Kathmandu | L2: =SUMIFS(Datasheet!$H:$H,Datasheet!$C:$C,Analysis!K2) -> 988000 | M2: =SUMIFS(Datasheet!$J:$J,Datasheet!$C:$C,Analysis!K2) -> 198000 | N2: =M2/L2 -> 0.20040486 | P2: March | Q2: =SUMIFS(SalesData[Revenue],SalesData[Date],">="&DATE(2026,3,1),SalesData[Date],"<"&DATE(2026,4,1)) -> 1151000 | R2: =SUMIFS(SalesData[Profit],SalesData[Date],">="&DATE(2026,3,1),SalesData[Date],"<"&DATE(2026,4,1)) -> 259200 | S2: =R2/Q2 -> 0.22519548
A3: Total Cost | B3: =SUM(Datasheet!I:I) -> 1307400 | D3: Rahul | E3: =SUMIFS(Datasheet!$H:$H,Datasheet!$D:$D,Analysis!D3) -> 138000 | F3: =E3/$B$2 -> 0.082289803 | G3: =SUMIFS(Datasheet!$J:$J,Datasheet!$D:$D,Analysis!D3) -> 45200 | H3: =G3/E3 -> 0.32753623 | I3: =IF(H3<25%,"Review","Healthy") -> Healthy | K3: Lalitpur | L3: =SUMIFS(Datasheet!$H:$H,Datasheet!$C:$C,Analysis!K3) -> 138000 | M3: =SUMIFS(Datasheet!$J:$J,Datasheet!$C:$C,Analysis!K3) -> 45200 | N3: =M3/L3 -> 0.32753623 | P3: April | Q3: =SUMIFS(SalesData[Revenue],SalesData[Date],">="&DATE(2026,4,1),SalesData[Date],"<"&DATE(2026,5,1)) -> 526000 | R3: =SUMIFS(SalesData[Profit],SalesData[Date],">="&DATE(2026,4,1),SalesData[Date],"<"&DATE(2026,5,1)) -> 110400 | S3: =R3/Q3 -> 0.20988593
A4: Total Profit | B4: =SUM(Datasheet!J:J) -> 369600 | D4: Priya | E4: =SUMIFS(Datasheet!$H:$H,Datasheet!$D:$D,Analysis!D4) -> 640000 | F4: =E4/$B$2 -> 0.38163387 | G4: =SUMIFS(Datasheet!$J:$J,Datasheet!$D:$D,Analysis!D4) -> 126000 | H4: =G4/E4 -> 0.196875 | I4: =IF(H4<25%,"Review","Healthy") -> Review | K4: Pokhara | L4: =SUMIFS(Datasheet!$H:$H,Datasheet!$C:$C,Analysis!K4) -> 378000 | M4: =SUMIFS(Datasheet!$J:$J,Datasheet!$C:$C,Analysis!K4) -> 77200 | N4: =M4/L4 -> 0.2042328
A5: Total Units | B5: =SUM(Datasheet!G:G) -> 119 | D5: Suman | E5: =SUMIFS(Datasheet!$H:$H,Datasheet!$D:$D,Analysis!D5) -> 378000 | F5: =E5/$B$2 -> 0.2254025 | G5: =SUMIFS(Datasheet!$J:$J,Datasheet!$D:$D,Analysis!D5) -> 77200 | H5: =G5/E5 -> 0.2042328 | I5: =IF(H5<25%,"Review","Healthy") -> Review | K5: Bharatpur | L5: =SUMIFS(Datasheet!$H:$H,Datasheet!$C:$C,Analysis!K5) -> 173000 | M5: =SUMIFS(Datasheet!$J:$J,Datasheet!$C:$C,Analysis!K5) -> 49200 | N5: =M5/L5 -> 0.28439306
A6: Overall Profit Margin | B6: =SUM(Datasheet!J:J)/SUM(Datasheet!H:H) -> 0.22039356 | D6: Riya | E6: =SUMIFS(Datasheet!$H:$H,Datasheet!$D:$D,Analysis!D6) -> 173000 | F6: =E6/$B$2 -> 0.10316041 | G6: =SUMIFS(Datasheet!$J:$J,Datasheet!$D:$D,Analysis!D6) -> 49200 | H6: =G6/E6 -> 0.28439306 | I6: =IF(H6<25%,"Review","Healthy") -> Healthy
A7: Average Order Value | B7: =AVERAGE(Datasheet!H:H) -> 83850
A8: Number of Orders | B8: =COUNTA(SalesData[Order ID]) -> 20
A14: Who generates the most revenue | D14: =INDEX(D2:D6,MATCH(MAX(E2:E6),E2:E6,0)) -> Priya
A15: How dependent is the business on its top salesperson? | D15: =MAX(E2:E6)/B2 -> 0.38163387
A16: Month-over-month growth | D16: =(Q3-Q2)/Q2 -> -0.54300608
A17: Which region generated the highest revenue? | D17: =INDEX(K2:K5,MATCH(MAX(L2:L5),L2:L5,0)) -> Kathmandu
A18: Which region has the highest profit margin? | D18: =INDEX(K2:K5,MATCH(MAX(N2:N5),N2:N5,0)) -> Lalitpur
A19: Which salesperson should be flagged for review based on the 25% profit-margin rule? | D19: Priya,Anisha,Suman
A20: Did revenue increase or decrease from March to April? By what percentage? | D20: decreased by 54.30%
A22: Write 3 business recommendations based on your analysis.
A23: Priya generates the highest revenue but has a profit margin below 25%. Management should review the pricing, discounts, product mix, or costs associated with her sales to improve profitability.
A24: Kathmandu should remain a key revenue market, while the company should investigate Lalitpur's higher profit margin to identify practices that could be replicated in other regions.
A25: Priya contributes approximately 38.2% of total revenue, indicating a relatively high dependence on one salesperson.
A26: Revenue decreased by 54.3% from March to April. Management should investigate the reasons for the sharp decline and develop actions to stabilize monthly sales.

Sheet 12-Pivot_Analysis
A7: Row Labels | B7: Sum of Revenue | C7: Sum of Profit | D7: Profit Margin | F7: Row Labels | G7: Sum of Revenue | H7: Sum of Profit | I7: Sum of Units | K7: Row Labels | L7: Sum of Revenue | M7: Sum of Profit | N7: Sum of Units | P7: Row Labels | Q7: Sum of Revenue | R7: Sum of Profit | S7: Sum of Units | U7: Row Labels | V7: Sum of Revenue | W7: Sum of Profit
A8: Kathmandu | B8: 988000 | C8: 198000 | D8: =GETPIVOTDATA("Sum of Profit",$A$7,"Region","Kathmandu")/GETPIVOTDATA("Sum of Revenue",$A$7,"Region","Kathmandu") -> 0.20040486 | F8: Priya | G8: 640000 | H8: 126000 | I8: 13 | K8: Accessories | L8: 207000 | M8: 79600 | N8: 86 | P8: Laptop | Q8: 960000 | R8: 168000 | S8: 12 | U8: 2026 | V8: 1677000 | W8: 369600
A9: Pokhara | B9: 378000 | C9: 77200 | D9: =GETPIVOTDATA("Sum of Profit",$A$7,"Region","Pokhara")/GETPIVOTDATA("Sum of Revenue",$A$7,"Region","Pokhara") -> 0.2042328 | F9: Suman | G9: 378000 | H9: 77200 | I9: 13 | K9: Electronics | L9: 1470000 | M9: 290000 | N9: 33 | P9: Monitor | Q9: 480000 | R9: 112000 | S9: 16 | U9: Mar | V9: 1151000 | W9: 259200
A10: Bharatpur | B10: 173000 | C10: 49200 | D10: =GETPIVOTDATA("Sum of Profit",$A$7,"Region","Bharatpur")/GETPIVOTDATA("Sum of Revenue",$A$7,"Region","Bharatpur") -> 0.28439306 | F10: Anisha | G10: 348000 | H10: 72000 | I10: 13 | K10: Grand Total | L10: 1677000 | M10: 369600 | N10: 119 | P10: Keyboard | Q10: 84000 | R10: 33600 | S10: 28 | U10: Apr | V10: 526000 | W10: 110400
A11: Lalitpur | B11: 138000 | C11: 45200 | D11: =GETPIVOTDATA("Sum of Profit",$A$7,"Region","Lalitpur")/GETPIVOTDATA("Sum of Revenue",$A$7,"Region","Lalitpur") -> 0.32753623 | F11: Riya | G11: 173000 | H11: 49200 | I11: 36 | P11: Webcam | Q11: 78000 | R11: 26000 | S11: 13 | U11: Grand Total | V11: 1677000 | W11: 369600
A12: Grand Total | B12: 1677000 | C12: 369600 | F12: Rahul | G12: 138000 | H12: 45200 | I12: 44 | P12: Mouse | Q12: 75000 | R12: 30000 | S12: 50
F13: Grand Total | G13: 1677000 | H13: 369600 | I13: 119 | P13: Grand Total | Q13: 1677000 | R13: 369600 | S13: 119
A32: Which region has the highest revenue? | F32: Kathmandu
A33: Which region has the highest profit? | F33: Kathmandu
A34: Which region has the highest profit margin? | F34: Lalitpur
A35: Which salesperson has the highest revenue? | F35: Priya
A36: Which salesperson generates the highest profit? | F36: Priya
A37: Which category generates the highest revenue? | F37: Electronics
A38: Which product generates the highest revenue? | F38: Laptop
A39: Which month has higher revenue — March or April? | F39: March
A40: What is the percentage change in revenue between the two months? | F40: =(GETPIVOTDATA("Sum of Revenue",$U$7,"Months (Date)",3,"Years (Date)",2026)-GETPIVOTDATA("Sum of Revenue",$U$7,"Months (Date)",4,"Years (Date)",2026))/GETPIVOTDATA("Sum of Revenue",$U$7,"Months (Date)",3,"Years (Date)",2026) -> 0.54300608 | G40: decrease
A42: Using the PivotTables and slicers, write 3 business insights.
A43: Kathmandu should remain a key revenue market, while the company should investigate Lalitpur's higher profit margin to identify practices that could be replicated in other regions.
A44: Priya contributes approximately 38.2% of total revenue, indicating a relatively high dependence on one salesperson.
A45: Revenue decreased by 54.3% from March to April. Management should investigate the reasons for the sharp decline and develop actions to stabilize monthly sales.

Sheet 13-Dashboard
B1: SALES PERFORMANCE DASHBOARD
E2: March-April 2026
C4: Revenue Growth | E4: Total Revenue | G4: Total Profit | I4: Total Orders | K4: Total Profit Margin
C5: =Analysis!D16 -> -0.54300608 | E5: =Analysis!B2 -> 1677000 | G5: =Analysis!B4 -> 369600 | I5: =Analysis!B8 -> 20 | K5: =Analysis!B6 -> 0.22039356
C8: Revenue by Region | I8: Revenue by Month
C18: Salesperson Performance | I18: Product Performance
C31: Business Insights
B32: Kathmandu should remain a key revenue market, while the company should investigate Lalitpur's higher profit margin to identify practices that could be replicated in other regions.
B33: Priya contributes approximately 38.2% of total revenue, indicating a relatively high dependence on one salesperson.
B34: Revenue decreased by 54.3% from March to April. Management should investigate the reasons for the sharp decline and develop actions to stabilize monthly sales.

Sheet 14-CaseStudy
A1: SALES PERFORMANCE CASE STUDY | J1: Monthly Analysis | Q1: Product Analysis
A2: Question | B2: Your Answer | J2: Metric | K2: March | L2: April | M2: Change | N2: Growth % | Q2: Product | R2: March Revenue | S2: April Revenue | T2: Change
A3: 1. Why did April revenue fall? | B3: April revenue fell mainly because of a sharp decline in Kathmandu revenue and a major drop in Monitor sales. Kathmandu declined by ₹388,000, while Monitor revenue fell by ₹360,000. | J3: Revenue | K3: =SUMIFS(Datasheet!H:H,Datasheet!B:B,">="&DATE(2026,3,1),Datasheet!B:B,"<"&DATE(2026,4,1)) -> 1151000 | L3: =SUMIFS(Datasheet!H:H,Datasheet!B:B,">="&DATE(2026,4,1),Datasheet!B:B,"<"&DATE(2026,5,1)) -> 526000 | M3: =L3-K3 -> -625000 | N3: =M3/K3 -> -0.54300608 | Q3: Laptop | R3: =SUMIFS(Datasheet!$H:$H,Datasheet!F:F,Q3,Datasheet!$B:$B,">="&DATE(2026,3,1),Datasheet!$B:$B,"<"&DATE(2026,4,1)) -> 560000 | S3: =SUMIFS(Datasheet!$H:$H,Datasheet!F:F,Q3,Datasheet!$B:$B,">="&DATE(2026,4,1),Datasheet!$B:$B,"<"&DATE(2026,5,1)) -> 400000 | T3: =S3-R3 -> -160000
A4: 2. Which region contributed most to the decline? | B4: =INDEX(J12:J15,MATCH(MIN(M12:M15),M12:M15,0)) -> Kathmandu | J4: Profit | K4: =SUMIFS(Datasheet!J:J,Datasheet!B:B,">="&DATE(2026,3,1),Datasheet!B:B,"<"&DATE(2026,4,1)) -> 259200 | L4: =SUMIFS(Datasheet!J:J,Datasheet!B:B,">="&DATE(2026,4,1),Datasheet!B:B,"<"&DATE(2026,5,1)) -> 110400 | M4: =L4-K4 -> -148800 | N4: =M4/K4 -> -0.57407407 | Q4: Mouse | R4: =SUMIFS(Datasheet!$H:$H,Datasheet!F:F,Q4,Datasheet!$B:$B,">="&DATE(2026,3,1),Datasheet!$B:$B,"<"&DATE(2026,4,1)) -> 45000 | S4: =SUMIFS(Datasheet!$H:$H,Datasheet!F:F,Q4,Datasheet!$B:$B,">="&DATE(2026,4,1),Datasheet!$B:$B,"<"&DATE(2026,5,1)) -> 30000 | T4: =S4-R4 -> -15000
A5: 3. Which salesperson contributed most to the decline? | B5: =INDEX(Q12:Q16,MATCH(MIN(T12:T16),T12:T16,0)) -> Anisha | J5: Orders | K5: =COUNTIFS(Datasheet!$B:$B,">="&DATE(2026,3,1),Datasheet!$B:$B,"<"&DATE(2026,4,1)) -> 15 | L5: =COUNTIFS(Datasheet!$B:$B,">="&DATE(2026,4,1),Datasheet!$B:$B,"<"&DATE(2026,5,1)) -> 5 | M5: =L5-K5 -> -10 | N5: =M5/K5 -> -0.66666667 | Q5: Monitor | R5: =SUMIFS(Datasheet!$H:$H,Datasheet!F:F,Q5,Datasheet!$B:$B,">="&DATE(2026,3,1),Datasheet!$B:$B,"<"&DATE(2026,4,1)) -> 420000 | S5: =SUMIFS(Datasheet!$H:$H,Datasheet!F:F,Q5,Datasheet!$B:$B,">="&DATE(2026,4,1),Datasheet!$B:$B,"<"&DATE(2026,5,1)) -> 60000 | T5: =S5-R5 -> -360000
A6: 4. Which product/category performed poorly? | B6: =INDEX(Q3:Q7,MATCH(MIN(T3:T7),T3:T7,0)) -> Monitor | J6: Units | K6: =SUMIFS(Datasheet!G:G,Datasheet!B:B,">="&DATE(2026,3,1),Datasheet!B:B,"<"&DATE(2026,4,1)) -> 80 | L6: =SUMIFS(Datasheet!G:G,Datasheet!B:B,">="&DATE(2026,4,1),Datasheet!B:B,"<"&DATE(2026,5,1)) -> 39 | M6: =L6-K6 -> -41 | N6: =M6/K6 -> -0.5125 | Q6: Keyboard | R6: =SUMIFS(Datasheet!$H:$H,Datasheet!F:F,Q6,Datasheet!$B:$B,">="&DATE(2026,3,1),Datasheet!$B:$B,"<"&DATE(2026,4,1)) -> 48000 | S6: =SUMIFS(Datasheet!$H:$H,Datasheet!F:F,Q6,Datasheet!$B:$B,">="&DATE(2026,4,1),Datasheet!$B:$B,"<"&DATE(2026,5,1)) -> 36000 | T6: =S6-R6 -> -12000
A7: 5. Did profitability also decline? | B7: Yes. Profit declined from ₹259,200 to ₹110,400, while profit margin decreased from 22.52% to 20.99%. | J7: Profit Margin | K7: =K4/K3 -> 0.22519548 | L7: =L4/L3 -> 0.20988593 | M7: =L7-K7 -> -0.015309551 | Q7: Webcam | R7: =SUMIFS(Datasheet!$H:$H,Datasheet!F:F,Q7,Datasheet!$B:$B,">="&DATE(2026,3,1),Datasheet!$B:$B,"<"&DATE(2026,4,1)) -> 78000 | S7: =SUMIFS(Datasheet!$H:$H,Datasheet!F:F,Q7,Datasheet!$B:$B,">="&DATE(2026,4,1),Datasheet!$B:$B,"<"&DATE(2026,5,1)) -> 0 | T7: =S7-R7 -> -78000
A8: 6. What is the biggest business risk? | B8: The biggest business risk is the sharp dependence on key revenue sources, particularly Kathmandu and major products such as Monitor and Laptop. The significant decline in these areas caused a large overall revenue and profit reduction in April.
A9: 7. What should management do?
A10: 1. Investigate: Investigate the reasons for the sharp decline in Kathmandu and Monitor sales, including stock availability, customer demand, pricing and salesperson performance. 2. Recover: Develop a recovery plan for Monitor sales and focus sales efforts on high-potential customers and regions while maintaining Laptop performance. 3. Reduce risk: Diversify revenue across products and regions to reduce dependence on a small number of major revenue sources and monitor performance weekly. | J10: Region Analysis | Q10: SalesPerson Analysis
J11: Region | K11: March Revenue | L11: April Revenue | M11: Change | N11: Growth % | Q11: Salesperson | R11: March Revenue | S11: April Revenue | T11: Change | U11: Growth %
J12: Kathmandu | K12: =SUMIFS(Datasheet!$H:$H,Datasheet!$C:$C,J12,Datasheet!$B:$B,">="&DATE(2026,3,1),Datasheet!$B:$B,"<"&DATE(2026,4,1)) -> 688000 | L12: =SUMIFS(Datasheet!$H:$H,Datasheet!$C:$C,J12,Datasheet!$B:$B,">="&DATE(2026,4,1),Datasheet!$B:$B,"<"&DATE(2026,5,1)) -> 300000 | M12: =L12-K12 -> -388000 | N12: =M12/K12 -> -0.56395349 | Q12: Anisha | R12: =SUMIFS(Datasheet!$H:$H,Datasheet!D:D,Q12,Datasheet!$B:$B,">="&DATE(2026,3,1),Datasheet!$B:$B,"<"&DATE(2026,4,1)) -> 288000 | S12: =SUMIFS(Datasheet!$H:$H,Datasheet!D:D,Q12,Datasheet!$B:$B,">="&DATE(2026,4,1),Datasheet!$B:$B,"<"&DATE(2026,5,1)) -> 60000 | T12: =S12-R12 -> -228000 | U12: =T12/R12 -> -0.79166667
J13: Lalitpur | K13: =SUMIFS(Datasheet!$H:$H,Datasheet!$C:$C,J13,Datasheet!$B:$B,">="&DATE(2026,3,1),Datasheet!$B:$B,"<"&DATE(2026,4,1)) -> 108000 | L13: =SUMIFS(Datasheet!$H:$H,Datasheet!$C:$C,J13,Datasheet!$B:$B,">="&DATE(2026,4,1),Datasheet!$B:$B,"<"&DATE(2026,5,1)) -> 30000 | M13: =L13-K13 -> -78000 | N13: =M13/K13 -> -0.72222222 | Q13: Rahul | R13: =SUMIFS(Datasheet!$H:$H,Datasheet!D:D,Q13,Datasheet!$B:$B,">="&DATE(2026,3,1),Datasheet!$B:$B,"<"&DATE(2026,4,1)) -> 108000 | S13: =SUMIFS(Datasheet!$H:$H,Datasheet!D:D,Q13,Datasheet!$B:$B,">="&DATE(2026,4,1),Datasheet!$B:$B,"<"&DATE(2026,5,1)) -> 30000 | T13: =S13-R13 -> -78000 | U13: =T13/R13 -> -0.72222222
J14: Pokhara | K14: =SUMIFS(Datasheet!$H:$H,Datasheet!$C:$C,J14,Datasheet!$B:$B,">="&DATE(2026,3,1),Datasheet!$B:$B,"<"&DATE(2026,4,1)) -> 218000 | L14: =SUMIFS(Datasheet!$H:$H,Datasheet!$C:$C,J14,Datasheet!$B:$B,">="&DATE(2026,4,1),Datasheet!$B:$B,"<"&DATE(2026,5,1)) -> 160000 | M14: =L14-K14 -> -58000 | N14: =M14/K14 -> -0.26605505 | Q14: Priya | R14: =SUMIFS(Datasheet!$H:$H,Datasheet!D:D,Q14,Datasheet!$B:$B,">="&DATE(2026,3,1),Datasheet!$B:$B,"<"&DATE(2026,4,1)) -> 400000 | S14: =SUMIFS(Datasheet!$H:$H,Datasheet!D:D,Q14,Datasheet!$B:$B,">="&DATE(2026,4,1),Datasheet!$B:$B,"<"&DATE(2026,5,1)) -> 240000 | T14: =S14-R14 -> -160000 | U14: =T14/R14 -> -0.4
J15: Bharatpur | K15: =SUMIFS(Datasheet!$H:$H,Datasheet!$C:$C,J15,Datasheet!$B:$B,">="&DATE(2026,3,1),Datasheet!$B:$B,"<"&DATE(2026,4,1)) -> 137000 | L15: =SUMIFS(Datasheet!$H:$H,Datasheet!$C:$C,J15,Datasheet!$B:$B,">="&DATE(2026,4,1),Datasheet!$B:$B,"<"&DATE(2026,5,1)) -> 36000 | M15: =L15-K15 -> -101000 | N15: =M15/K15 -> -0.73722628 | Q15: Suman | R15: =SUMIFS(Datasheet!$H:$H,Datasheet!D:D,Q15,Datasheet!$B:$B,">="&DATE(2026,3,1),Datasheet!$B:$B,"<"&DATE(2026,4,1)) -> 218000 | S15: =SUMIFS(Datasheet!$H:$H,Datasheet!D:D,Q15,Datasheet!$B:$B,">="&DATE(2026,4,1),Datasheet!$B:$B,"<"&DATE(2026,5,1)) -> 160000 | T15: =S15-R15 -> -58000 | U15: =T15/R15 -> -0.26605505
Q16: Riya | R16: =SUMIFS(Datasheet!$H:$H,Datasheet!D:D,Q16,Datasheet!$B:$B,">="&DATE(2026,3,1),Datasheet!$B:$B,"<"&DATE(2026,4,1)) -> 137000 | S16: =SUMIFS(Datasheet!$H:$H,Datasheet!D:D,Q16,Datasheet!$B:$B,">="&DATE(2026,4,1),Datasheet!$B:$B,"<"&DATE(2026,5,1)) -> 36000 | T16: =S16-R16 -> -101000 | U16: =T16/R16 -> -0.73722628

Sheet 15-MiniProject
A1: KPI | B1: Value | E1: Region Analysis | K1: SalesPerson Analysis | Q1: Product Analysis | V1: Monthly Analysis
A2: Total Revenue | B2: =SUM(Datasheet!H:H) -> 1677000 | E2: Region | F2: March Revenue | G2: April Revenue | H2: Change | I2: Growth % | K2: Salesperson | L2: March Revenue | M2: April Revenue | N2: Change | O2: Growth % | Q2: Product | R2: March Revenue | S2: April Revenue | T2: Change | V2: Metric | W2: March | X2: April | Y2: Change | Z2: Growth %
A3: Total Cost | B3: =SUM(Datasheet!I:I) -> 1307400 | E3: Kathmandu | F3: =SUMIFS(Datasheet!$H:$H,Datasheet!$C:$C,E3,Datasheet!$B:$B,">="&DATE(2026,3,1),Datasheet!$B:$B,"<"&DATE(2026,4,1)) -> 688000 | G3: =SUMIFS(Datasheet!$H:$H,Datasheet!$C:$C,E3,Datasheet!$B:$B,">="&DATE(2026,4,1),Datasheet!$B:$B,"<"&DATE(2026,5,1)) -> 300000 | H3: =G3-F3 -> -388000 | I3: =H3/F3 -> -0.56395349 | K3: Anisha | L3: =SUMIFS(Datasheet!$H:$H,Datasheet!$D:$D,K3,Datasheet!$B:$B,">="&DATE(2026,3,1),Datasheet!$B:$B,"<"&DATE(2026,4,1)) -> 288000 | M3: =SUMIFS(Datasheet!$H:$H,Datasheet!$D:$D,K3,Datasheet!$B:$B,">="&DATE(2026,4,1),Datasheet!$B:$B,"<"&DATE(2026,5,1)) -> 60000 | N3: =M3-L3 -> -228000 | O3: =N3/L3 -> -0.79166667 | Q3: Laptop | R3: =SUMIFS(Datasheet!$H:$H,Datasheet!F:F,Q3,Datasheet!$B:$B,">="&DATE(2026,3,1),Datasheet!$B:$B,"<"&DATE(2026,4,1)) -> 560000 | S3: =SUMIFS(Datasheet!$H:$H,Datasheet!F:F,Q3,Datasheet!$B:$B,">="&DATE(2026,4,1),Datasheet!$B:$B,"<"&DATE(2026,5,1)) -> 400000 | T3: =S3-R3 -> -160000 | V3: Revenue | W3: =SUMIFS(Datasheet!$H:$H,Datasheet!$B:$B,">="&DATE(2026,3,1),Datasheet!$B:$B,"<"&DATE(2026,4,1)) -> 1151000 | X3: =SUMIFS(Datasheet!$H:$H,Datasheet!$B:$B,">="&DATE(2026,4,1),Datasheet!$B:$B,"<"&DATE(2026,5,1)) -> 526000 | Y3: =X3-W3 -> -625000 | Z3: =Y3/W3 -> -0.54300608
A4: Total Profit | B4: =SUM(Datasheet!J:J) -> 369600 | E4: Lalitpur | F4: =SUMIFS(Datasheet!$H:$H,Datasheet!$C:$C,E4,Datasheet!$B:$B,">="&DATE(2026,3,1),Datasheet!$B:$B,"<"&DATE(2026,4,1)) -> 108000 | G4: =SUMIFS(Datasheet!$H:$H,Datasheet!$C:$C,E4,Datasheet!$B:$B,">="&DATE(2026,4,1),Datasheet!$B:$B,"<"&DATE(2026,5,1)) -> 30000 | H4: =G4-F4 -> -78000 | I4: =H4/F4 -> -0.72222222 | K4: Rahul | L4: =SUMIFS(Datasheet!$H:$H,Datasheet!$D:$D,K4,Datasheet!$B:$B,">="&DATE(2026,3,1),Datasheet!$B:$B,"<"&DATE(2026,4,1)) -> 108000 | M4: =SUMIFS(Datasheet!$H:$H,Datasheet!$D:$D,K4,Datasheet!$B:$B,">="&DATE(2026,4,1),Datasheet!$B:$B,"<"&DATE(2026,5,1)) -> 30000 | N4: =M4-L4 -> -78000 | O4: =N4/L4 -> -0.72222222 | Q4: Mouse | R4: =SUMIFS(Datasheet!$H:$H,Datasheet!F:F,Q4,Datasheet!$B:$B,">="&DATE(2026,3,1),Datasheet!$B:$B,"<"&DATE(2026,4,1)) -> 45000 | S4: =SUMIFS(Datasheet!$H:$H,Datasheet!F:F,Q4,Datasheet!$B:$B,">="&DATE(2026,4,1),Datasheet!$B:$B,"<"&DATE(2026,5,1)) -> 30000 | T4: =S4-R4 -> -15000 | V4: Profit | W4: =SUMIFS(Datasheet!J:J,Datasheet!$B:$B,">="&DATE(2026,3,1),Datasheet!$B:$B,"<"&DATE(2026,4,1)) -> 259200 | X4: =SUMIFS(Datasheet!J:J,Datasheet!B:B,">="&DATE(2026,4,1),Datasheet!B:B,"<"&DATE(2026,5,1)) -> 110400 | Y4: =X4-W4 -> -148800 | Z4: =Y4/W4 -> -0.57407407
A5: Total Units | B5: =SUM(Datasheet!G:G) -> 119 | E5: Pokhara | F5: =SUMIFS(Datasheet!$H:$H,Datasheet!$C:$C,E5,Datasheet!$B:$B,">="&DATE(2026,3,1),Datasheet!$B:$B,"<"&DATE(2026,4,1)) -> 218000 | G5: =SUMIFS(Datasheet!$H:$H,Datasheet!$C:$C,E5,Datasheet!$B:$B,">="&DATE(2026,4,1),Datasheet!$B:$B,"<"&DATE(2026,5,1)) -> 160000 | H5: =G5-F5 -> -58000 | I5: =H5/F5 -> -0.26605505 | K5: Priya | L5: =SUMIFS(Datasheet!$H:$H,Datasheet!$D:$D,K5,Datasheet!$B:$B,">="&DATE(2026,3,1),Datasheet!$B:$B,"<"&DATE(2026,4,1)) -> 400000 | M5: =SUMIFS(Datasheet!$H:$H,Datasheet!$D:$D,K5,Datasheet!$B:$B,">="&DATE(2026,4,1),Datasheet!$B:$B,"<"&DATE(2026,5,1)) -> 240000 | N5: =M5-L5 -> -160000 | O5: =N5/L5 -> -0.4 | Q5: Monitor | R5: =SUMIFS(Datasheet!$H:$H,Datasheet!F:F,Q5,Datasheet!$B:$B,">="&DATE(2026,3,1),Datasheet!$B:$B,"<"&DATE(2026,4,1)) -> 420000 | S5: =SUMIFS(Datasheet!$H:$H,Datasheet!F:F,Q5,Datasheet!$B:$B,">="&DATE(2026,4,1),Datasheet!$B:$B,"<"&DATE(2026,5,1)) -> 60000 | T5: =S5-R5 -> -360000 | V5: Orders | W5: =COUNTIFS(Datasheet!$B:$B,">="&DATE(2026,3,1),Datasheet!$B:$B,"<"&DATE(2026,4,1)) -> 15 | X5: =COUNTIFS(Datasheet!$B:$B,">="&DATE(2026,4,1),Datasheet!$B:$B,"<"&DATE(2026,5,1)) -> 5 | Y5: =X5-W5 -> -10 | Z5: =Y5/W5 -> -0.66666667
A6: Overall Profit Margin | B6: =SUM(Datasheet!J:J)/SUM(Datasheet!H:H) -> 0.22039356 | E6: Bharatpur | F6: =SUMIFS(Datasheet!$H:$H,Datasheet!$C:$C,E6,Datasheet!$B:$B,">="&DATE(2026,3,1),Datasheet!$B:$B,"<"&DATE(2026,4,1)) -> 137000 | G6: =SUMIFS(Datasheet!$H:$H,Datasheet!$C:$C,E6,Datasheet!$B:$B,">="&DATE(2026,4,1),Datasheet!$B:$B,"<"&DATE(2026,5,1)) -> 36000 | H6: =G6-F6 -> -101000 | I6: =H6/F6 -> -0.73722628 | K6: Suman | L6: =SUMIFS(Datasheet!$H:$H,Datasheet!$D:$D,K6,Datasheet!$B:$B,">="&DATE(2026,3,1),Datasheet!$B:$B,"<"&DATE(2026,4,1)) -> 218000 | M6: =SUMIFS(Datasheet!$H:$H,Datasheet!$D:$D,K6,Datasheet!$B:$B,">="&DATE(2026,4,1),Datasheet!$B:$B,"<"&DATE(2026,5,1)) -> 160000 | N6: =M6-L6 -> -58000 | O6: =N6/L6 -> -0.26605505 | Q6: Keyboard | R6: =SUMIFS(Datasheet!$H:$H,Datasheet!F:F,Q6,Datasheet!$B:$B,">="&DATE(2026,3,1),Datasheet!$B:$B,"<"&DATE(2026,4,1)) -> 48000 | S6: =SUMIFS(Datasheet!$H:$H,Datasheet!F:F,Q6,Datasheet!$B:$B,">="&DATE(2026,4,1),Datasheet!$B:$B,"<"&DATE(2026,5,1)) -> 36000 | T6: =S6-R6 -> -12000 | V6: Units | W6: =SUMIFS(Datasheet!G:G,Datasheet!B:B,">="&DATE(2026,3,1),Datasheet!B:B,"<"&DATE(2026,4,1)) -> 80 | X6: =SUMIFS(Datasheet!G:G,Datasheet!B:B,">="&DATE(2026,4,1),Datasheet!B:B,"<"&DATE(2026,5,1)) -> 39 | Y6: =X6-W6 -> -41 | Z6: =Y6/W6 -> -0.5125
A7: Average Order Value | B7: =AVERAGE(Datasheet!H:H) -> 83850 | K7: Riya | L7: =SUMIFS(Datasheet!$H:$H,Datasheet!$D:$D,K7,Datasheet!$B:$B,">="&DATE(2026,3,1),Datasheet!$B:$B,"<"&DATE(2026,4,1)) -> 137000 | M7: =SUMIFS(Datasheet!$H:$H,Datasheet!$D:$D,K7,Datasheet!$B:$B,">="&DATE(2026,4,1),Datasheet!$B:$B,"<"&DATE(2026,5,1)) -> 36000 | N7: =M7-L7 -> -101000 | O7: =N7/L7 -> -0.73722628 | Q7: Webcam | R7: =SUMIFS(Datasheet!$H:$H,Datasheet!F:F,Q7,Datasheet!$B:$B,">="&DATE(2026,3,1),Datasheet!$B:$B,"<"&DATE(2026,4,1)) -> 78000 | S7: =SUMIFS(Datasheet!$H:$H,Datasheet!F:F,Q7,Datasheet!$B:$B,">="&DATE(2026,4,1),Datasheet!$B:$B,"<"&DATE(2026,5,1)) -> 0 | T7: =S7-R7 -> -78000 | V7: Profit Margin | W7: =W4/W3 -> 0.22519548 | X7: =X4/X3 -> 0.20988593 | Y7: =X7-W7 -> -0.015309551
A8: Number of Orders | B8: =COUNTA(SalesData[Order ID]) -> 20
A22: Why did April perform worse than March?
A23: April revenue declined substantially compared with March, primarily due to a sharp decline in Kathmandu revenue and a major drop in Monitor sales. Kathmandu revenue decreased by ₹388,000, while Monitor revenue decreased by ₹360,000.
A25: Biggest Problem
A26: Kathmandu lost ₹388,000 and Monitor lost ₹360,000 in revenue from March to April, creating significant dependence on a small number of products and regions.
A28: Recommendation
A29: Investigate the sharp decline in Kathmandu & Monitor sales...
A30: Develop a recovery plan for Monitor sales while maintaining laptop sales.
A31: Diversify revenue across products and regions to reduce dependence on a small number of major revenue sources, and monitor performance weekly.
A33: Executive Summary
A34: Company revenue declined by 54.30% from March to April.
A35: Kathmandu, the highest-revenue region in March, experienced a substantial decline in April. Monitor sales also decreased significantly.
A36: Management should investigate the sharp declines in Kathmandu and Monitor sales, develop a recovery plan, and establish weekly performance monitoring.
... A39: Pokhara and Suman showed comparatively stronger performance, experiencing the smallest revenue declines among regions and salespeople respectively.

Sheet 16-FinalAssesment
A1: KPI | B1: Value | E1: Salesperson | F1: Revenue | G1: Profit | H1: Profit Margin | K1: Region | L1: Revenue | M1: Profit | N1: Profit Margin | Q1: Product | R1: Revenue | S1: Profit | T1: Units | U1: Profit Margin
A2: Total Revenue | B2: =SUM(Datasheet!H:H) -> 1677000 | E2: Priya | F2: =SUMIFS(Datasheet!H:H,Datasheet!D:D,E2) -> 640000 | G2: =SUMIFS(Datasheet!J:J,Datasheet!D:D,E2) -> 126000 | H2: =G2/F2 -> 0.196875 | K2: Kathmandu | L2: =SUMIFS(Datasheet!$H:$H,Datasheet!$C:$C,K2) -> 988000 | M2: =SUMIFS(Datasheet!$J:$J,Datasheet!$C:$C,K2) -> 198000 | N2: =M2/L2 -> 0.20040486 | Q2: Laptop | R2: =SUMIFS(Datasheet!$H:$H,Datasheet!$F:$F,'16-FinalAssesment'!Q2) -> 960000 | S2: =SUMIFS(Datasheet!$J:$J,Datasheet!$F:$F,'16-FinalAssesment'!Q2) -> 168000 | T2: =SUMIFS(Datasheet!G:G,Datasheet!F:F,'16-FinalAssesment'!Q2) -> 12 | U2: =S2/R2 -> 0.175
A3: Total Cost | B3: =SUM(Datasheet!I:I) -> 1307400 | E3: Suman | F3: =SUMIFS(Datasheet!H:H,Datasheet!D:D,E3) -> 378000 | G3: =SUMIFS(Datasheet!J:J,Datasheet!D:D,E3) -> 77200 | H3: =G3/F3 -> 0.2042328 | K3: Pokhara | L3: =SUMIFS(Datasheet!$H:$H,Datasheet!$C:$C,K3) -> 378000 | M3: =SUMIFS(Datasheet!$J:$J,Datasheet!$C:$C,K3) -> 77200 | N3: =M3/L3 -> 0.2042328 | Q3: Mouse | R3: =SUMIFS(Datasheet!$H:$H,Datasheet!$F:$F,'16-FinalAssesment'!Q3) -> 75000 | S3: =SUMIFS(Datasheet!$J:$J,Datasheet!$F:$F,'16-FinalAssesment'!Q3) -> 30000 | T3: =SUMIFS(Datasheet!G:G,Datasheet!F:F,'16-FinalAssesment'!Q3) -> 50 | U3: =S3/R3 -> 0.4
A4: Total Profit | B4: =SUM(Datasheet!J:J) -> 369600 | E4: Anisha | F4: =SUMIFS(Datasheet!H:H,Datasheet!D:D,E4) -> 348000 | G4: =SUMIFS(Datasheet!J:J,Datasheet!D:D,E4) -> 72000 | H4: =G4/F4 -> 0.20689655 | K4: Bharatpur | L4: =SUMIFS(Datasheet!$H:$H,Datasheet!$C:$C,K4) -> 173000 | M4: =SUMIFS(Datasheet!$J:$J,Datasheet!$C:$C,K4) -> 49200 | N4: =M4/L4 -> 0.28439306 | Q4: Monitor | R4: =SUMIFS(Datasheet!$H:$H,Datasheet!$F:$F,'16-FinalAssesment'!Q4) -> 480000 | S4: =SUMIFS(Datasheet!$J:$J,Datasheet!$F:$F,'16-FinalAssesment'!Q4) -> 112000 | T4: =SUMIFS(Datasheet!G:G,Datasheet!F:F,'16-FinalAssesment'!Q4) -> 16 | U4: =S4/R4 -> 0.23333333
A5: Total Units | B5: =SUM(Datasheet!G:G) -> 119 | E5: Riya | F5: =SUMIFS(Datasheet!H:H,Datasheet!D:D,E5) -> 173000 | G5: =SUMIFS(Datasheet!J:J,Datasheet!D:D,E5) -> 49200 | H5: =G5/F5 -> 0.28439306 | K5: Lalitpur | L5: =SUMIFS(Datasheet!$H:$H,Datasheet!$C:$C,K5) -> 138000 | M5: =SUMIFS(Datasheet!$J:$J,Datasheet!$C:$C,K5) -> 45200 | N5: =M5/L5 -> 0.32753623 | Q5: Webcam | R5: =SUMIFS(Datasheet!$H:$H,Datasheet!$F:$F,'16-FinalAssesment'!Q6) -> 84000 | S5: =SUMIFS(Datasheet!$J:$J,Datasheet!$F:$F,'16-FinalAssesment'!Q6) -> 33600 | T5: =SUMIFS(Datasheet!G:G,Datasheet!F:F,'16-FinalAssesment'!Q5) -> 13 | U5: =S5/R5 -> 0.4
A6: Overall Profit Margin | B6: =SUM(Datasheet!J:J)/SUM(Datasheet!H:H) -> 0.22039356 | E6: Rahul | F6: =SUMIFS(Datasheet!H:H,Datasheet!D:D,E6) -> 138000 | G6: =SUMIFS(Datasheet!J:J,Datasheet!D:D,E6) -> 45200 | H6: =G6/F6 -> 0.32753623 | Q6: Keyboard | R6: =SUMIFS(Datasheet!$H:$H,Datasheet!$F:$F,'16-FinalAssesment'!Q5) -> 78000 | S6: =SUMIFS(Datasheet!$J:$J,Datasheet!$F:$F,'16-FinalAssesment'!Q5) -> 26000 | T6: =SUMIFS(Datasheet!G:G,Datasheet!F:F,'16-FinalAssesment'!Q6) -> 28 | U6: =S6/R6 -> 0.33333333
E8: SalesPerson Analysis | K8: Region Analysis | Q8: Product Analysis
E9: Salesperson | F9: March Revenue | G9: April Revenue | H9: Change | I9: Growth % | K9: Region | L9: March Revenue | M9: April Revenue | N9: Change | O9: Growth % | Q9: Product | R9: March Revenue | S9: April Revenue | T9: Change
E10: Anisha | F10: =SUMIFS(Datasheet!$H:$H,Datasheet!$D:$D,E10,Datasheet!$B:$B,">="&DATE(2026,3,1),Datasheet!$B:$B,"<"&DATE(2026,4,1)) -> 288000 | G10: =SUMIFS(Datasheet!$H:$H,Datasheet!$D:$D,E10,Datasheet!$B:$B,">="&DATE(2026,4,1),Datasheet!$B:$B,"<"&DATE(2026,5,1)) -> 60000 | H10: =G10-F10 -> -228000 | I10: =H10/F10 -> -0.79166667 | K10: Kathmandu | L10: =SUMIFS(Datasheet!$H:$H,Datasheet!$C:$C,K10,Datasheet!$B:$B,">="&DATE(2026,3,1),Datasheet!$B:$B,"<"&DATE(2026,4,1)) -> 688000 | M10: =SUMIFS(Datasheet!$H:$H,Datasheet!$C:$C,K10,Datasheet!$B:$B,">="&DATE(2026,4,1),Datasheet!$B:$B,"<"&DATE(2026,5,1)) -> 300000 | N10: =M10-L10 -> -388000 | O10: =N10/L10 -> -0.56395349 | Q10: Laptop | R10: =SUMIFS(Datasheet!$H:$H,Datasheet!F:F,Q10,Datasheet!$B:$B,">="&DATE(2026,3,1),Datasheet!$B:$B,"<"&DATE(2026,4,1)) -> 560000 | S10: =SUMIFS(Datasheet!$H:$H,Datasheet!F:F,Q10,Datasheet!$B:$B,">="&DATE(2026,4,1),Datasheet!$B:$B,"<"&DATE(2026,5,1)) -> 400000 | T10: =S10-R10 -> -160000
E11: Rahul | F11: =SUMIFS(Datasheet!$H:$H,Datasheet!$D:$D,E11,Datasheet!$B:$B,">="&DATE(2026,3,1),Datasheet!$B:$B,"<"&DATE(2026,4,1)) -> 108000 | G11: =SUMIFS(Datasheet!$H:$H,Datasheet!$D:$D,E11,Datasheet!$B:$B,">="&DATE(2026,4,1),Datasheet!$B:$B,"<"&DATE(2026,5,1)) -> 30000 | H11: =G11-F11 -> -78000 | I11: =H11/F11 -> -0.72222222 | K11: Lalitpur | L11: =SUMIFS(Datasheet!$H:$H,Datasheet!$C:$C,K11,Datasheet!$B:$B,">="&DATE(2026,3,1),Datasheet!$B:$B,"<"&DATE(2026,4,1)) -> 108000 | M11: =SUMIFS(Datasheet!$H:$H,Datasheet!$C:$C,K11,Datasheet!$B:$B,">="&DATE(2026,4,1),Datasheet!$B:$B,"<"&DATE(2026,5,1)) -> 30000 | N11: =M11-L11 -> -78000 | O11: =N11/L11 -> -0.72222222 | Q11: Mouse | R11: =SUMIFS(Datasheet!$H:$H,Datasheet!F:F,Q11,Datasheet!$B:$B,">="&DATE(2026,3,1),Datasheet!$B:$B,"<"&DATE(2026,4,1)) -> 45000 | S11: =SUMIFS(Datasheet!$H:$H,Datasheet!F:F,Q11,Datasheet!$B:$B,">="&DATE(2026,4,1),Datasheet!$B:$B,"<"&DATE(2026,5,1)) -> 30000 | T11: =S11-R11 -> -15000
E12: Priya | F12: =SUMIFS(Datasheet!$H:$H,Datasheet!$D:$D,E12,Datasheet!$B:$B,">="&DATE(2026,3,1),Datasheet!$B:$B,"<"&DATE(2026,4,1)) -> 400000 | G12: =SUMIFS(Datasheet!$H:$H,Datasheet!$D:$D,E12,Datasheet!$B:$B,">="&DATE(2026,4,1),Datasheet!$B:$B,"<"&DATE(2026,5,1)) -> 240000 | H12: =G12-F12 -> -160000 | I12: =H12/F12 -> -0.4 | K12: Pokhara | L12: =SUMIFS(Datasheet!$H:$H,Datasheet!$C:$C,K12,Datasheet!$B:$B,">="&DATE(2026,3,1),Datasheet!$B:$B,"<"&DATE(2026,4,1)) -> 218000 | M12: =SUMIFS(Datasheet!$H:$H,Datasheet!$C:$C,K12,Datasheet!$B:$B,">="&DATE(2026,4,1),Datasheet!$B:$B,"<"&DATE(2026,5,1)) -> 160000 | N12: =M12-L12 -> -58000 | O12: =N12/L12 -> -0.26605505 | Q12: Monitor | R12: =SUMIFS(Datasheet!$H:$H,Datasheet!F:F,Q12,Datasheet!$B:$B,">="&DATE(2026,3,1),Datasheet!$B:$B,"<"&DATE(2026,4,1)) -> 420000 | S12: =SUMIFS(Datasheet!$H:$H,Datasheet!F:F,Q12,Datasheet!$B:$B,">="&DATE(2026,4,1),Datasheet!$B:$B,"<"&DATE(2026,5,1)) -> 60000 | T12: =S12-R12 -> -360000
E13: Suman | F13: =SUMIFS(Datasheet!$H:$H,Datasheet!$D:$D,E13,Datasheet!$B:$B,">="&DATE(2026,3,1),Datasheet!$B:$B,"<"&DATE(2026,4,1)) -> 218000 | G13: =SUMIFS(Datasheet!$H:$H,Datasheet!$D:$D,E13,Datasheet!$B:$B,">="&DATE(2026,4,1),Datasheet!$B:$B,"<"&DATE(2026,5,1)) -> 160000 | H13: =G13-F13 -> -58000 | I13: =H13/F13 -> -0.26605505 | K13: Bharatpur | L13: =SUMIFS(Datasheet!$H:$H,Datasheet!$C:$C,K13,Datasheet!$B:$B,">="&DATE(2026,3,1),Datasheet!$B:$B,"<"&DATE(2026,4,1)) -> 137000 | M13: =SUMIFS(Datasheet!$H:$H,Datasheet!$C:$C,K13,Datasheet!$B:$B,">="&DATE(2026,4,1),Datasheet!$B:$B,"<"&DATE(2026,5,1)) -> 36000 | N13: =M13-L13 -> -101000 | O13: =N13/L13 -> -0.73722628 | Q13: Keyboard | R13: =SUMIFS(Datasheet!$H:$H,Datasheet!F:F,Q13,Datasheet!$B:$B,">="&DATE(2026,3,1),Datasheet!$B:$B,"<"&DATE(2026,4,1)) -> 48000 | S13: =SUMIFS(Datasheet!$H:$H,Datasheet!F:F,Q13,Datasheet!$B:$B,">="&DATE(2026,4,1),Datasheet!$B:$B,"<"&DATE(2026,5,1)) -> 36000 | T13: =S13-R13 -> -12000
E14: Riya | F14: =SUMIFS(Datasheet!$H:$H,Datasheet!$D:$D,E14,Datasheet!$B:$B,">="&DATE(2026,3,1),Datasheet!$B:$B,"<"&DATE(2026,4,1)) -> 137000 | G14: =SUMIFS(Datasheet!$H:$H,Datasheet!$D:$D,E14,Datasheet!$B:$B,">="&DATE(2026,4,1),Datasheet!$B:$B,"<"&DATE(2026,5,1)) -> 36000 | H14: =G14-F14 -> -101000 | I14: =H14/F14 -> -0.73722628 | Q14: Webcam | R14: =SUMIFS(Datasheet!$H:$H,Datasheet!F:F,Q14,Datasheet!$B:$B,">="&DATE(2026,3,1),Datasheet!$B:$B,"<"&DATE(2026,4,1)) -> 78000 | S14: =SUMIFS(Datasheet!$H:$H,Datasheet!F:F,Q14,Datasheet!$B:$B,">="&DATE(2026,4,1),Datasheet!$B:$B,"<"&DATE(2026,5,1)) -> 0 | T14: =S14-R14 -> -78000
A24: Biggest Business Problem | C24: Kathmandu revenue decreased from Rs. 688000 to Rs. 300000 which equals to loss of 388000 in revenue from March to April, creating significant dependence on a small number of products and regions.
A26: Positive Insight | C26: Pokhara showed the strongest regional resilience, with revenue declining by only ₹58,000 (-26.61%) from March to April, the smallest decline among the four regions.
C27: Suman showed comparatively strong performance, with the smallest salesperson revenue decline of ₹58,000 (-26.61%) from March to April.
A29: Management Recommendation | C29: 1. Investigate: Investigate the reasons for the sharp decline in Kathmandu and Monitor sales, including stock availability, customer demand, pricing and salesperson performance.
C30: 2. Recover: Develop a recovery plan for Monitor sales and focus sales efforts on high-potential customers and regions while maintaining Laptop performance.
C31: 3. Reduce risk: Diversify revenue across products and regions to reduce dependence on a small number of major revenue sources and monitor performance weekly.
A33: Executive Summary | C33: Company revenue declined by 54.30% from March to April.
C34: Kathmandu, the highest-revenue region in March, experienced a substantial decline in April. Monitor sales also decreased significantly.
C35: Management should investigate the sharp declines in Kathmandu and Monitor sales, develop a recovery plan, and establish weekly performance monitoring.
A37: Additional Question | C37: Did the smaller order cause the decline? | G37: pricing/discount data
C38: Was the lack of stock the problem? | G38: marketing data
C39: Was low customer demand the problem? | G39: cancellation data
