Workbook

Sheet Sheet1
A1: Order ID | B1: Date | C1: Region | D1: Salesperson | E1: Category | F1: Product | G1: Units | H1: Revenue | I1: Cost | J1: Profit | K1: Profit Margin | L1: Revenue per Units
A2: O001 | B2: 46023 | C2: Kathmandu | D2: Anisha | E2: Electronics | F2: Laptop | G2: 2 | H2: 160000 | I2: 132000 | J2: =SalesData[[#This Row],[Revenue]]-SalesData[[#This Row],[Cost]] -> 28000 | K2: =SalesData[[#This Row],[Profit]]/SalesData[[#This Row],[Revenue]] -> 0.175 | L2: =SalesData[[#This Row],[Revenue]]/SalesData[[#This Row],[Units]] -> 80000
A3: O002 | B3: 46025 | C3: Lalitpur | D3: Rahul | E3: Accessories | F3: Mouse | G3: 10 | H3: 15000 | I3: 9000 | J3: =SalesData[[#This Row],[Revenue]]-SalesData[[#This Row],[Cost]] -> 6000 | K3: =SalesData[[#This Row],[Profit]]/SalesData[[#This Row],[Revenue]] -> 0.4 | L3: =SalesData[[#This Row],[Revenue]]/SalesData[[#This Row],[Units]] -> 1500
A4: O003 | B4: 46027 | C4: Kathmandu | D4: Priya | E4: Electronics | F4: Monitor | G4: 3 | H4: 90000 | I4: 69000 | J4: =SalesData[[#This Row],[Revenue]]-SalesData[[#This Row],[Cost]] -> 21000 | K4: =SalesData[[#This Row],[Profit]]/SalesData[[#This Row],[Revenue]] -> 0.23333333 | L4: =SalesData[[#This Row],[Revenue]]/SalesData[[#This Row],[Units]] -> 30000
A5: O004 | B5: 46030 | C5: Pokhara | D5: Suman | E5: Accessories | F5: Keyboard | G5: 5 | H5: 15000 | I5: 9000 | J5: =SalesData[[#This Row],[Revenue]]-SalesData[[#This Row],[Cost]] -> 6000 | K5: =SalesData[[#This Row],[Profit]]/SalesData[[#This Row],[Revenue]] -> 0.4 | L5: =SalesData[[#This Row],[Revenue]]/SalesData[[#This Row],[Units]] -> 3000
A6: O005 | B6: 46034 | C6: Bharatpur | D6: Riya | E6: Electronics | F6: Webcam | G6: 4 | H6: 24000 | I6: 16000 | J6: =SalesData[[#This Row],[Revenue]]-SalesData[[#This Row],[Cost]] -> 8000 | K6: =SalesData[[#This Row],[Profit]]/SalesData[[#This Row],[Revenue]] -> 0.33333333 | L6: =SalesData[[#This Row],[Revenue]]/SalesData[[#This Row],[Units]] -> 6000
A7: O006 | B7: 46037 | C7: Kathmandu | D7: Anisha | E7: Electronics | F7: Laptop | G7: 1 | H7: 80000 | I7: 66000 | J7: =SalesData[[#This Row],[Revenue]]-SalesData[[#This Row],[Cost]] -> 14000 | K7: =SalesData[[#This Row],[Profit]]/SalesData[[#This Row],[Revenue]] -> 0.175 | L7: =SalesData[[#This Row],[Revenue]]/SalesData[[#This Row],[Units]] -> 80000
A8: O007 | B8: 46042 | C8: Lalitpur | D8: Rahul | E8: Electronics | F8: Monitor | G8: 2 | H8: 60000 | I8: 46000 | J8: =SalesData[[#This Row],[Revenue]]-SalesData[[#This Row],[Cost]] -> 14000 | K8: =SalesData[[#This Row],[Profit]]/SalesData[[#This Row],[Revenue]] -> 0.23333333 | L8: =SalesData[[#This Row],[Revenue]]/SalesData[[#This Row],[Units]] -> 30000
A9: O008 | B9: 46047 | C9: Pokhara | D9: Suman | E9: Electronics | F9: Laptop | G9: 1 | H9: 80000 | I9: 66000 | J9: =SalesData[[#This Row],[Revenue]]-SalesData[[#This Row],[Cost]] -> 14000 | K9: =SalesData[[#This Row],[Profit]]/SalesData[[#This Row],[Revenue]] -> 0.175 | L9: =SalesData[[#This Row],[Revenue]]/SalesData[[#This Row],[Units]] -> 80000
A10: O009 | B10: 46055 | C10: Bharatpur | D10: Riya | E10: Accessories | F10: Mouse | G10: 15 | H10: 22500 | I10: 13500 | J10: =SalesData[[#This Row],[Revenue]]-SalesData[[#This Row],[Cost]] -> 9000 | K10: =SalesData[[#This Row],[Profit]]/SalesData[[#This Row],[Revenue]] -> 0.4 | L10: =SalesData[[#This Row],[Revenue]]/SalesData[[#This Row],[Units]] -> 1500
A11: O010 | B11: 46058 | C11: Kathmandu | D11: Priya | E11: Electronics | F11: Laptop | G11: 2 | H11: 160000 | I11: 132000 | J11: =SalesData[[#This Row],[Revenue]]-SalesData[[#This Row],[Cost]] -> 28000 | K11: =SalesData[[#This Row],[Profit]]/SalesData[[#This Row],[Revenue]] -> 0.175 | L11: =SalesData[[#This Row],[Revenue]]/SalesData[[#This Row],[Units]] -> 80000
A12: O011 | B12: 46063 | C12: Lalitpur | D12: Rahul | E12: Accessories | F12: Keyboard | G12: 8 | H12: 24000 | I12: 14400 | J12: =SalesData[[#This Row],[Revenue]]-SalesData[[#This Row],[Cost]] -> 9600 | K12: =SalesData[[#This Row],[Profit]]/SalesData[[#This Row],[Revenue]] -> 0.4 | L12: =SalesData[[#This Row],[Revenue]]/SalesData[[#This Row],[Units]] -> 3000
A13: O012 | B13: 46067 | C13: Pokhara | D13: Suman | E13: Electronics | F13: Monitor | G13: 4 | H13: 120000 | I13: 92000 | J13: =SalesData[[#This Row],[Revenue]]-SalesData[[#This Row],[Cost]] -> 28000 | K13: =SalesData[[#This Row],[Profit]]/SalesData[[#This Row],[Revenue]] -> 0.23333333 | L13: =SalesData[[#This Row],[Revenue]]/SalesData[[#This Row],[Units]] -> 30000
... A16: O015 | B16: 46081 | C16: Kathmandu | D16: Priya | E16: Electronics | F16: Monitor | G16: 5 | H16: 150000 | I16: 115000 | J16: =SalesData[[#This Row],[Revenue]]-SalesData[[#This Row],[Cost]] -> 35000 | K16: =SalesData[[#This Row],[Profit]]/SalesData[[#This Row],[Revenue]] -> 0.23333333 | L16: =SalesData[[#This Row],[Revenue]]/SalesData[[#This Row],[Units]] -> 30000

Sheet Analysis
A1: KPI | B1: Value | D1: Region | E1: Revenue | G1: Salesperson | H1: Revenue | I1: Profit | J1: Profit Margin | L1: Product | M1: Revenue | O1: Category | P1: Profit
A2: Total Revenue | B2: =SUM(Sheet1!H:H) -> 1116500 | D2: Kathmandu | E2: =SUMIFS(Sheet1!H:H,Sheet1!C:C,Analysis!D2) -> 676000 | G2: Suman | H2: =SUMIFS(Sheet1!H:H,Sheet1!D:D,Analysis!G2) -> 215000 | I2: =SUMIFS(Sheet1!J:J,Sheet1!D:D,Analysis!G2) -> 48000 | J2: =I2/H2 -> 0.22325581 | L2: Laptop | M2: =SUMIFS(Sheet1!H:H,Sheet1!F:F,Analysis!L2) -> 560000 | O2: Electronics | P2: =SUMIFS(Sheet1!J:J,Sheet1!E:E,Analysis!O2) -> 204000
A3: Total Cost | B3: =SUM(Sheet1!I:I) -> 869900 | D3: Pokhara | E3: =SUMIFS(Sheet1!H:H,Sheet1!C:C,Analysis!D4) -> 126500 | G3: Riya | H3: =SUMIFS(Sheet1!H:H,Sheet1!D:D,Analysis!G3) -> 126500 | I3: =SUMIFS(Sheet1!J:J,Sheet1!D:D,Analysis!G3) -> 31000 | J3: =I3/H3 -> 0.24505929 | L3: Monitor | M3: =SUMIFS(Sheet1!H:H,Sheet1!F:F,Analysis!L3) -> 420000 | O3: Accessories | P3: =SUMIFS(Sheet1!J:J,Sheet1!E:E,Analysis!O3) -> 42600
A4: Total Profit | B4: =SUM(Sheet1!J:J) -> 246600 | D4: Bharatpur | E4: =SUMIFS(Sheet1!H:H,Sheet1!C:C,Analysis!D5) -> 99000 | G4: Rahul | H4: =SUMIFS(Sheet1!H:H,Sheet1!D:D,Analysis!G4) -> 99000 | I4: =SUMIFS(Sheet1!J:J,Sheet1!D:D,Analysis!G4) -> 29600 | J4: =I4/H4 -> 0.2989899 | L4: Webcam | M4: =SUMIFS(Sheet1!H:H,Sheet1!F:F,Analysis!L4) -> 60000
A5: Total Units | B5: =SUM(Sheet1!G:G) -> 69 | D5: Lalitpur | E5: =SUMIFS(Sheet1!H:H,Sheet1!C:C,Analysis!D3) -> 215000 | G5: Priya | H5: =SUMIFS(Sheet1!H:H,Sheet1!D:D,Analysis!G5) -> 400000 | I5: =SUMIFS(Sheet1!J:J,Sheet1!D:D,Analysis!G5) -> 84000 | J5: =I5/H5 -> 0.21 | L5: Keyboard | M5: =SUMIFS(Sheet1!H:H,Sheet1!F:F,Analysis!L5) -> 39000
A6: Average Order Value | B6: =AVERAGE(Sheet1!H:H) -> 74433.333 | G6: Anisha | H6: =SUMIFS(Sheet1!H:H,Sheet1!D:D,Analysis!G6) -> 276000 | I6: =SUMIFS(Sheet1!J:J,Sheet1!D:D,Analysis!G6) -> 54000 | J6: =I6/H6 -> 0.19565217 | L6: Mouse | M6: =SUMIFS(Sheet1!H:H,Sheet1!F:F,Analysis!L6) -> 37500
A7: Overall Profit Margin | B7: =SUM(Sheet1!J:J)/SUM(Sheet1!H:H) -> 0.22086879
G11: Month | H11: Revenue
A12: Which region generated the highest revenue? | B12: Kathmandu | G12: January | H12: =SUMIFS(Sheet1!H:H,Sheet1!B:B,">="&DATE(2026,1,1),Sheet1!B:B,"<"&DATE(2026,2,1)) -> 524000
A13: Which salesperson generated the highest revenue? | B13: Priya | G13: February | H13: =SUMIFS(Sheet1!H:H,Sheet1!B:B,">="&DATE(2026,2,1),Sheet1!B:B,"<"&DATE(2026,3,1)) -> 592500
A14: Which product generated the highest revenue? | B14: Laptop
A15: Which category generated the highest profit? | B15: Electronics
A16: Which salesperson has the highest profit margin? | B16: Rahul | G16: Revenue Changed | I16: =H13-H12 -> 68500
A17: Did revenue increase from January to February? | B17: =IF(H13>H12,"Yes, revenue increased","No, revenue decreased") -> Yes, revenue increased | G17: Growth % | I17: =I16/MAX(H12,H13) -> 0.11561181

Sheet Day10-Analysis
A1: Salesperson | B1: Revenue | C1: Rank | D1: % of Total revenue | E1: Target | F1: Variance | G1: Achievement % | H1: Status | L1: Month | M1: Revenue | N1: Target | O1: Variance | P1: Achievement %
A2: Priya | B2: =SUMIFS(Sheet1!H:H,Sheet1!D:D,A2) -> 400000 | C2: =_xlfn.RANK.EQ(B2,$B$2:$B$6,0) -> 1 | D2: ='Day10-Analysis'!B5/Analysis!$B$2 -> 0.11330049 | E2: 200000 | F2: =B2-E2 -> 200000 | G2: =B2/E2 -> 2 | H2: =IF(G2>=1,"Target Achieved","Below target") -> Target Achieved | L2: January | M2: =SUMIFS(Sheet1!H:H,Sheet1!B:B,">="&DATE(2026,1,1),Sheet1!B:B,"<"&DATE(2026,2,1)) -> 524000 | N2: 500000 | O2: =M2-N2 -> 24000 | P2: =M2/N2 -> 1.048
A3: Anisha | B3: =SUMIFS(Sheet1!H:H,Sheet1!D:D,A3) -> 276000 | C3: =_xlfn.RANK.EQ(B3,$B$2:$B$6,0) -> 2 | D3: ='Day10-Analysis'!B6/Analysis!$B$2 -> 0.088669951 | E3: 200000 | F3: =B3-E3 -> 76000 | G3: =B3/E3 -> 1.38 | H3: =IF(G3>=1,"Target Achieved","Below target") -> Target Achieved | L3: February | M3: =SUMIFS(Sheet1!H:H,Sheet1!B:B,">="&DATE(2026,2,1),Sheet1!B:B,"<"&DATE(2026,3,1)) -> 592500 | N3: 550000 | O3: =M3-N3 -> 42500 | P3: =M3/N3 -> 1.0772727
A4: Suman | B4: =SUMIFS(Sheet1!H:H,Sheet1!D:D,A4) -> 215000 | C4: =_xlfn.RANK.EQ(B4,$B$2:$B$6,0) -> 3 | D4: ='Day10-Analysis'!B2/Analysis!$B$2 -> 0.35826243 | E4: 200000 | F4: =B4-E4 -> 15000 | G4: =B4/E4 -> 1.075 | H4: =IF(G4>=1,"Target Achieved","Below target") -> Target Achieved
A5: Riya | B5: =SUMIFS(Sheet1!H:H,Sheet1!D:D,A5) -> 126500 | C5: =_xlfn.RANK.EQ(B5,$B$2:$B$6,0) -> 4 | D5: ='Day10-Analysis'!B3/Analysis!$B$2 -> 0.24720107 | E5: 200000 | F5: =B5-E5 -> -73500 | G5: =B5/E5 -> 0.6325 | H5: =IF(G5>=1,"Target Achieved","Below target") -> Below target
A6: Rahul | B6: =SUMIFS(Sheet1!H:H,Sheet1!D:D,A6) -> 99000 | C6: =_xlfn.RANK.EQ(B6,$B$2:$B$6,0) -> 5 | D6: ='Day10-Analysis'!B4/Analysis!$B$2 -> 0.19256605 | E6: 200000 | F6: =B6-E6 -> -101000 | G6: =B6/E6 -> 0.495 | H6: =IF(G6>=1,"Target Achieved","Below target") -> Below target
L9: Product | M9: Revenue | N9: % of total | O9: Cumulative % | P9: Profit | Q9: Profit Margin | R9: Business Flag
L10: Laptop | M10: =SUMIFS(Sheet1!H:H,Sheet1!F:F,L10) -> 560000 | N10: =M10/SUM($M$10:$M$14) -> 0.5015674 | O10: =N10 -> 0.5015674 | P10: =SUMIFS(Sheet1!J:J,Sheet1!F:F,'Day10-Analysis'!L10) -> 98000 | Q10: =P10/M10 -> 0.175 | R10: =IF(AND(M10>=200000,Q10>=20%),"High Priority", IF(AND(M10>=50000,Q10>=20%),"Good","Review")) -> Review
L11: Monitor | M11: =SUMIFS(Sheet1!H:H,Sheet1!F:F,L11) -> 420000 | N11: =M11/SUM($M$10:$M$14) -> 0.37617555 | O11: =O10+N11 -> 0.87774295 | P11: =SUMIFS(Sheet1!J:J,Sheet1!F:F,'Day10-Analysis'!L11) -> 98000 | Q11: =P11/M11 -> 0.23333333 | R11: =IF(AND(M11>=200000,Q11>=20%),"High Priority", IF(AND(M11>=50000,Q11>=20%),"Good","Review")) -> High Priority
A12: Who is the #1 salesperson by revenue? | H12: =INDEX(A2:A6,MATCH(1,C2:C6,0)) -> Priya | L12: Webcam | M12: =SUMIFS(Sheet1!H:H,Sheet1!F:F,L12) -> 60000 | N12: =M12/SUM($M$10:$M$14) -> 0.053739364 | O12: =O11+N12 -> 0.93148231 | P12: =SUMIFS(Sheet1!J:J,Sheet1!F:F,'Day10-Analysis'!L12) -> 20000 | Q12: =P12/M12 -> 0.33333333 | R12: =IF(AND(M12>=200000,Q12>=20%),"High Priority", IF(AND(M12>=50000,Q12>=20%),"Good","Review")) -> Good
A13: Which salesperson contributes the largest percentage of company revenue? | H13: =INDEX(A2:A6,MATCH(MAX(D2:D6),D2:D6,0)) -> Suman | L13: Keyboard | M13: =SUMIFS(Sheet1!H:H,Sheet1!F:F,L13) -> 39000 | N13: =M13/SUM($M$10:$M$14) -> 0.034930587 | O13: =O12+N13 -> 0.9664129 | P13: =SUMIFS(Sheet1!J:J,Sheet1!F:F,'Day10-Analysis'!L13) -> 15600 | Q13: =P13/M13 -> 0.4 | R13: =IF(AND(M13>=200000,Q13>=20%),"High Priority", IF(AND(M13>=50000,Q13>=20%),"Good","Review")) -> Review
L14: Mouse | M14: =SUMIFS(Sheet1!H:H,Sheet1!F:F,L14) -> 37500 | N14: =M14/SUM($M$10:$M$14) -> 0.033587103 | O14: =O13+N14 -> 1 | P14: =SUMIFS(Sheet1!J:J,Sheet1!F:F,'Day10-Analysis'!L14) -> 15000 | Q14: =P14/M14 -> 0.4 | R14: =IF(AND(M14>=200000,Q14>=20%),"High Priority", IF(AND(M14>=50000,Q14>=20%),"Good","Review")) -> Review
A18: Business Insights
A20: 1. Priya generated the highest revenue at ₹400,000, ranking first among the salespeople.
A21: 2. February revenue was ₹592,500 compared with ₹524,000 in January, representing approximately 13.07% growth.
A22: 3. The business should investigate why some salespeople are significantly below the ₹200,000 target and identify what is driving Priya's stronger performance.
